nuorder/__init__.py
nuorder/__main__.py
nuorder/_metadata.py
nuorder/ini_config.py
nuorder/util.py
nuorder-1.1.2.dist-info/METADATA
nuorder-1.1.2.dist-info/RECORD
nuorder-1.1.2.dist-info/WHEEL
nuorder-1.1.2.dist-info/entry_points.txt
nuorder-1.1.2.dist-info/top_level.txt
