Metadata-Version: 2.1
Name: nuorder
Version: 1.1.2
Summary: Package to make requests to NuOrder's wholesale API
Home-page: https://github.com/jmagnusson/nuorder
Author: Jacob Magnusson
Author-email: m@jacobian.se
License: BSD
Platform: any
Classifier: Development Status :: 5 - Production/Stable
Classifier: Environment :: Web Environment
Classifier: Intended Audience :: Developers
Classifier: License :: OSI Approved :: BSD License
Classifier: Operating System :: OS Independent
Classifier: Programming Language :: Python
Classifier: Programming Language :: Python :: 3.5
Classifier: Programming Language :: Python :: 3.6
Classifier: Programming Language :: Python :: 3.7
Provides-Extra: cli
Provides-Extra: test
Requires-Dist: requests
Provides-Extra: cli
Requires-Dist: argh; extra == 'cli'
Requires-Dist: ipython; extra == 'cli'
Requires-Dist: termcolor; extra == 'cli'
Provides-Extra: test
Requires-Dist: coverage (>=4.3.4); extra == 'test'
Requires-Dist: responses (>=0.5.1); extra == 'test'
Requires-Dist: pytest (>=3.0.7); extra == 'test'
Requires-Dist: flake8 (>=3.3.0); extra == 'test'
